{
	"class" : {
		"initialize" : "BenjaminVanRyseghem 2/24/2011 18:01" },
	"instance" : {
		"appJs" : "CamilloBruni 3/3/2013 01:44",
		"bbqJs" : "CamilloBruni 3/9/2013 00:13",
		"commonCss" : "CamilloBruni 3/9/2013 00:13",
		"documentForFile:" : "CamilloBruni 4/21/2011 13:37",
		"fulllistCss" : "CamilloBruni 3/9/2013 00:13",
		"fulllistJs" : "CamilloBruni 3/3/2013 01:39",
		"jquerybabbqJs" : "CamilloBruni 3/9/2013 00:13",
		"mainCss" : "CamilloBruni 3/9/2013 00:13",
		"mainJs" : "CamilloBruni 3/9/2013 19:50",
		"searchCss" : "CamilloBruni 3/9/2013 00:13",
		"searchJs" : "CamilloBruni 3/9/2013 00:12",
		"stcodeCss" : "CamilloBruni 3/9/2013 00:12",
		"styleCss" : "CamilloBruni 3/9/2013 00:17",
		"vtipCss" : "CamilloBruni 3/9/2013 00:12" } }
